PyAto/PyAto.py
PyAto/__init__.py
PyAto_navanchauhan-0.0.3.dist-info/LICENSE
PyAto_navanchauhan-0.0.3.dist-info/METADATA
PyAto_navanchauhan-0.0.3.dist-info/WHEEL
PyAto_navanchauhan-0.0.3.dist-info/top_level.txt
PyAto_navanchauhan-0.0.3.dist-info/RECORD
