Metadata-Version: 2.1
Name: PyAto-navanchauhan
Version: 0.0.3
Summary: Python Wrapper for Zomato API
Home-page: https://github.com/navanchauhan/PyAto
Author: Navan Chauhan
Author-email: navanchauhan@gmail.com
License: UNKNOWN
Platform: UNKNOWN
Classifier: Programming Language :: Python :: 3
Classifier: License :: OSI Approved :: MIT License
Classifier: Operating System :: OS Independent
